pyweb_moderator_api/__init__.py
pyweb_moderator_api/async_example.py
pyweb_moderator_api/sync_example.py
pyweb_moderator_api-1.2.0.dist-info/METADATA
pyweb_moderator_api-1.2.0.dist-info/WHEEL
pyweb_moderator_api-1.2.0.dist-info/top_level.txt
pyweb_moderator_api-1.2.0.dist-info/RECORD
