Metadata-Version: 2.1
Name: pyweb-moderator-api
Version: 1.2.0
Summary: Library for using the API for PyWeb AI Moderator.
Home-page: https://github.com/pywebsol
Author: pywebsol
Author-email: pywebsolutions.ru@gmail.com
License: UNKNOWN
Project-URL: Telegram, https://t.me/RuModeratorAI_API_Bot
Keywords: antispam moderator ai api pyweb pywebsol
Platform: UNKNOWN
Classifier: Programming Language :: Python :: 3.11
Classifier: License :: OSI Approved :: MIT License
Classifier: Operating System :: OS Independent
Requires-Python: >=3.6
Requires-Dist: aiohttp
Requires-Dist: requests
Requires-Dist: urllib3
